msdsf22018/__init__.py
msdsf22018/Area_package/Area_module.py
msdsf22018/Area_package/__init__.py
msdsf22018/Area_package/volume_module.py
msdsf22018/calculatot_package/__init__.py
msdsf22018/calculatot_package/basic_mathOperation.py
azka-0.0.1.dist-info/METADATA
azka-0.0.1.dist-info/WHEEL
azka-0.0.1.dist-info/top_level.txt
azka-0.0.1.dist-info/RECORD
