Metadata-Version: 2.1
Name: azka
Version: 0.0.1
Summary: azka
Author: azka rathor
Author-email: azka.rathor1@gmail.com
Keywords: python,Area_module,Volume_module,area,basic_mathOperation
Classifier: Intended Audience :: Developers
Classifier: Programming Language :: Python :: 3
Classifier: Operating System :: Unix
Classifier: Operating System :: MacOS :: MacOS X
Classifier: Operating System :: Microsoft :: Windows
